my_own_package/__init__.py
paul_project_hello-0.2.0.dist-info/METADATA
paul_project_hello-0.2.0.dist-info/WHEEL
paul_project_hello-0.2.0.dist-info/top_level.txt
paul_project_hello-0.2.0.dist-info/RECORD
