Metadata-Version: 2.1
Name: paul-project-hello
Version: 0.2.0
Summary: says hello to user
Author: Paul C.
Author-email: paul.constantin0305@gmail.com
License: UNKNOWN
Platform: UNKNOWN
